hss_skill/__init__.py
hss_skill/hss.py
hss_skill/logger.py
hss_skill/rpc.py
hss_skill-0.5.0.dist-info/LICENSE
hss_skill-0.5.0.dist-info/METADATA
hss_skill-0.5.0.dist-info/WHEEL
hss_skill-0.5.0.dist-info/top_level.txt
hss_skill-0.5.0.dist-info/RECORD
