Metadata-Version: 2.1
Name: hss-skill
Version: 0.5.0
Summary: Library for creating voice assistant skills for the hermes skill server (hss-server)
Home-page: https://github.com/patrickjane/hss-skill
Author: Patrick Fial
Author-email: mg.m@gmx.net
License: UNKNOWN
Platform: UNKNOWN
Classifier: Programming Language :: Python :: 3
Classifier: License :: OSI Approved :: MIT License
Classifier: Operating System :: OS Independent
Requires-Python: >=3.7
